{"ih":{"w":"ih","p":"","t":"abbr. 测量端（Instrument Head）；间接加热（Indirect Heating）；反时针（Inverted Hour）"},"IH virus":{"w":"IH virus","p":"","t":"[医] 传染性肝炎病毒"},"iha":{"w":"iha","p":"","t":" [医][=anti-microsomal antibody]抗微粒体抗体"},"ihab":{"w":"ihab","p":"","t":"abbr. International Horticultural Advisory Bureau 国际园艺咨询局"},"ihas":{"w":"ihas","p":"","t":"abbr. integrated helicopter avionics system 直升飞机综合航空电子系统; integrated helmet assembly subsystem 集成头盔组件子系统"},"ihat":{"w":"ihat","p":"","t":" [医][=indirect haemagglutination test]间接血细胞凝集试验"},"ihb":{"w":"ihb","p":"","t":"abbr. International Hydrographic Bureau 国际航道局"},"ihc":{"w":"ihc","p":"'ɪhk","t":" [医][=idiopathic hemochromatosis]特发性血色素沉着（症）"},"ihd":{"w":"ihd","p":"","t":"abbr. International Hydrological Decade 国际水文十年（计划）"},"ihde":{"w":"ihde","p":"","t":" [人名] 伊德"},"ihds":{"w":"ihds","p":"","t":"abbr. inpatient hospital days 住院患者的住院天数; Interstate Highway and Defense System 州际公路与防卫系统"},"ihe":{"w":"ihe","p":"","t":" [医][=International Health Evaluation Association]国际健康鉴定协会"},"ihep":{"w":"ihep","p":"","t":"abbr. Institute of High Energy Physics （中国科学院）高能物理研究所"},"ihes":{"w":"ihes","p":"","t":"abbr. idiopathic hypereosinophilic syndrome 特发性嗜酸性粒细胞增多综合征"},"iheu":{"w":"iheu","p":"","t":"abbr. International Humanist and Ethical Union 国际人道主义与道德联合会; International Humanistic and Ethical Union 国际人文学与伦理学联合会"},"ihi":{"w":"ihi","p":"","t":" 佛氏竹刀鱼"},"ihl":{"w":"ihl","p":"","t":" [医][=International Homeopathic League]国际顺势疗法联合会"},"ihle":{"w":"ihle","p":"","t":" [人名] 伊尔; [地名] [德国] 伊勒河"},"Ihle's paste":{"w":"Ihle's paste","p":"","t":"[医] 伊耳氏糊(含雷琐辛、淀粉、氧化锌和软石蜡)"},"ihm":{"w":"ihm","p":"","t":"abbr. Iesus Mundi Salvator (Latin=Jesus, the Saviour of the World) （拉丁语）救世主; 耶稣; Institute of Hotel Marketing 旅店营销协会; Institute of Housing Managers 住房经理协会"},"ihn":{"w":"ihn","p":"","t":"abbr. in His name 以主的名义"},"ihome":{"w":"ihome","p":"","t":"abbr. information home 信息家庭"},"ihop":{"w":"ihop","p":"","t":"国际薄烤饼店（International House of Pancakes ）"},"ihp":{"w":"ihp","p":"","t":"abbr. indicated horsepower 指示马力; ischemic heart disease 缺血性心脏病"},"ihr":{"w":"ihr","p":"","t":"abbr. 内热耗（internal heat rate）；提高采收率方法；国际卫生条例"},"ihra":{"w":"ihra","p":"","t":"abbr. Independent Human Rights Association 独立人权协会"},"ihram":{"w":"ihram","p":"i'rɑ:m","t":"n. 伊斯兰教朝圣服, 穿朝圣服时的神圣状态"},"ihrigising":{"w":"ihrigising","p":"","t":"硅化法"},"Ihrigizing":{"w":"Ihrigizing","p":"i'ridʒiziŋ","t":"(=ihrigising)[冶]固体渗硅, 伊利格扩散渗硅法"},"ihs":{"w":"ihs","p":"","t":"(ih 的复数) abbr. 测量端（Instrument Head）；间接加热（Indirect Heating）；反时针（Inverted Hour）"},"ihsa":{"w":"ihsa","p":"","t":"abbr. iodinated human serum albumin 碘化人体血清蛋白"},"IHT":{"w":"IHT","p":"","t":"abbr. 《国际先驱论坛报》（International Herald Tribune）"}}