{"yp":{"w":"yp","p":"","t":"abbr. 黄页（yellow pages）；风光邮资明信片；屈服点（yield point）"},"ypc":{"w":"ypc","p":"","t":"abbr. Yangzi Petrochemical International Trading Company （中国南京）扬子石化国际贸易公司"},"yperite":{"w":"yperite","p":"'i: pәrait","t":"n. [化]芥子气(毒气的一种)"},"ypg":{"w":"ypg","p":"","t":"abbr. Yuma Proving Ground 尤马试验场"},"Yponomeutidae":{"w":"Yponomeutidae","p":"","t":"巢蛾科"},"Ypres":{"w":"Ypres","p":"'iprɔ","t":"n. 伊普尔（比利时西佛兰德省的一城市）"},"yps":{"w":"yps","p":"","t":"abbr. Port Hawkesbury;  Nova Scotia;  Canada 加拿大; 新斯科舍"},"ypsilanti":{"w":"ypsilanti","p":"","t":" [地名] [美国] 伊普西兰蒂"},"ypsiliform":{"w":"ypsiliform","p":"ip'silә,fɔ:m","t":"(孢子)Y形的"},"ypsiloid":{"w":"ypsiloid","p":"'i:psi,lɔid","t":"(=upsiloid)倒人字形的, V字形的"}}